{"ROWS":10,"COLS":20,"0x0":{"RESIDENT":"me"},"0x1":{},"0x2":{},"0x3":{},"0x4":{},"0x5":{},"0x6":{},"0x7":{},"0x8":{},"0x9":{},"0x10":{},"0x11":{},"0x12":{},"0x13":{},"0x14":{},"0x15":{},"0x16":{},"0x17":{},"0x18":{},"0x19":{},"1x0":{},"1x1":{},"1x2":{},"1x3":{},"1x4":{},"1x5":{},"1x6":{},"1x7":{},"1x8":{},"1x9":{},"1x10":{},"1x11":{},"1x12":{},"1x13":{},"1x14":{},"1x15":{},"1x16":{},"1x17":{},"1x18":{},"1x19":{},"2x0":{},"2x1":{},"2x2":{},"2x3":{},"2x4":{},"2x5":{"_II":0},"2x6":{"_II":1},"2x7":{"_II":2},"2x8":{"_II":3},"2x9":{"_II":4},"2x10":{"_II":5},"2x11":{"_II":1},"2x12":{"_II":6},"2x13":{"_II":7},"2x14":{"_II":4},"2x15":{"_II":8},"2x16":{},"2x17":{},"2x18":{},"2x19":{},"3x0":{},"3x1":{},"3x2":{},"3x3":{},"3x4":{},"3x5":{},"3x6":{},"3x7":{},"3x8":{},"3x9":{},"3x10":{},"3x11":{},"3x12":{},"3x13":{},"3x14":{},"3x15":{},"3x16":{},"3x17":{},"3x18":{},"3x19":{},"4x0":{},"4x1":{},"4x2":{},"4x3":{},"4x4":{},"4x5":{},"4x6":{"enteraction":"narrative \"<h1>We are an experimental group of Artists. Right?</h1>\"\ngame chain IntroA","desc":"To see About Us enter at A","_II":3},"4x7":{"desc":"To see About Us enter at A","_II":9},"4x8":{"desc":"To see About Us enter at A","_II":6},"4x9":{"desc":"To see About Us enter at A","_II":10},"4x10":{"desc":"To see About Us enter at A","_II":11},"4x11":{"desc":"To see About Us enter at A","_II":12},"4x12":{"desc":"To see About Us enter at A","_II":10},"4x13":{"desc":"To see About Us enter at A","_II":8},"4x14":{},"4x15":{},"4x16":{},"4x17":{},"4x18":{},"4x19":{},"5x0":{},"5x1":{},"5x2":{},"5x3":{},"5x4":{},"5x5":{},"5x6":{},"5x7":{},"5x8":{},"5x9":{},"5x10":{},"5x11":{},"5x12":{},"5x13":{},"5x14":{},"5x15":{},"5x16":{},"5x17":{},"5x18":{},"5x19":{},"6x0":{},"6x1":{},"6x2":{},"6x3":{},"6x4":{},"6x5":{},"6x6":{"enteraction":"narrative \"Board Game One\"\ngame chain IntroB\n","desc":"To see BoardGameOne, enter at B","_II":9},"6x7":{"desc":"To see BoardGameOne, enter at B","_II":6},"6x8":{"desc":"To see BoardGameOne, enter at B","_II":3},"6x9":{"desc":"To see BoardGameOne, enter at B","_II":1},"6x10":{"desc":"To see BoardGameOne, enter at B","_II":13},"6x11":{"desc":"To see BoardGameOne, enter at B","_II":14},"6x12":{"desc":"To see BoardGameOne, enter at B","_II":3},"6x13":{"desc":"To see BoardGameOne, enter at B","_II":15},"6x14":{"desc":"To see BoardGameOne, enter at B","_II":2},"6x15":{"desc":"To see BoardGameOne, enter at B","_II":6},"6x16":{"desc":"To see BoardGameOne, enter at B","_II":16},"6x17":{"desc":"To see BoardGameOne, enter at B","_II":2},"6x18":{},"6x19":{},"7x0":{},"7x1":{},"7x2":{},"7x3":{},"7x4":{},"7x5":{},"7x6":{},"7x7":{},"7x8":{},"7x9":{},"7x10":{},"7x11":{},"7x12":{},"7x13":{},"7x14":{},"7x15":{},"7x16":{},"7x17":{},"7x18":{},"7x19":{},"8x0":{},"8x1":{},"8x2":{},"8x3":{},"8x4":{},"8x5":{},"8x6":{},"8x7":{},"8x8":{},"8x9":{},"8x10":{},"8x11":{},"8x12":{},"8x13":{},"8x14":{},"8x15":{},"8x16":{},"8x17":{},"8x18":{},"8x19":{},"9x0":{},"9x1":{},"9x2":{},"9x3":{},"9x4":{},"9x5":{},"9x6":{},"9x7":{},"9x8":{},"9x9":{},"9x10":{},"9x11":{},"9x12":{},"9x13":{},"9x14":{},"9x15":{},"9x16":{},"9x17":{},"9x18":{},"9x19":{},"properties":{"title":"Freak Rocks Home","enteraction":"narrative \"Board Game One\"\ngame chain IntroB\n"},"PLAYERS":["me"],"ITEMS":[],"me":{"POV":"true","imagename":"players/dude"},"IMAGES":["alphabetic/F","alphabetic/R","alphabetic/E","alphabetic/A","alphabetic/K","alphabetic/dot","alphabetic/O","alphabetic/C","alphabetic/S","alphabetic/B","alphabetic/U","alphabetic/T","alphabetic/_","alphabetic/D","alphabetic/G","alphabetic/M","alphabetic/N"]}